rododendron/__init__.py
rododendron/rododendron.py
rododendron-0.0.1.dist-info/LICENSE
rododendron-0.0.1.dist-info/METADATA
rododendron-0.0.1.dist-info/WHEEL
rododendron-0.0.1.dist-info/top_level.txt
rododendron-0.0.1.dist-info/RECORD
